<?xml version="1.0" encoding="UTF-8"?>
<GUIProfiles>
	<Profile name="lpsBackground" extends="fs25_licensePlateDialogContainer">
        <size value="428px 670px"/>
        <position value="-580px -60px"/>
    </Profile>
	
	<Profile name="lpsHeader" extends="fs25_textDefault" with="anchorMiddleLeft">
        <textSize value="24px" />
        <textBold value="true" />
        <position value="0 0" />
		<size value="180px 40px"/>
    </Profile>

	<Profile name="lpsVehicleHeader" extends="lpsHeader">
		<textAlignment value="left"/>
        <textOffset value="25px 0px"/>
    </Profile>

	<Profile name="lpsLicensePlateHeader" extends="lpsHeader"  with="anchorMiddleRight">
		<textAlignment value="right"/>
        <textOffset value="-15px 0px"/>
    </Profile>

	<Profile name="lpsList" extends="list" with="anchorTopLeft">
		<position value="15px -20px"/>
        <size value="380px 550px"/>
		<isHorizontalList value="false" />
        <showHighlights value="true" />
    </Profile>

	<Profile name="lpsListItem" extends="fs25_settingsControlsListItem" with="alternating">
		<position value="0px 0px"/>
        <size value="360px 50px" />
        <!-- <imageColor value="$preset_colorListRowBackground"/>
        <imageFocusedColor value="$preset_colorFocusBackgroundGradient"/>
        <imageSelectedColor value="$preset_colorFocusBackgroundGradient"/> -->
    </Profile>

    <Profile name="lpsListItemHeader" extends="fs25_settingsControlsListItem" with="alternating">
		<position value="0px 0px"/>
        <size value="360px 50px" />

        <imageColor value="$preset_colorListRowBackground"/>
        <imageFocusedColor value="$preset_colorFocusBackgroundGradient"/>
        <imageSelectedColor value="$preset_colorFocusBackgroundGradient"/>
    </Profile>

	<Profile name="lpsVehicle" extends="fs25_textDefault" with="anchorTopLeft">
		<position value="0px 0px"/>
		<size value="190px 25px" />
        <textVerticalAlignment value="middle" />
        <textAutoWidth value="true" />
		<textDisabledColor value="$preset_colorRed"/>
    </Profile>
    <Profile name="lpsImplement" extends="fs25_textDefault" with="anchorBottomLeft">
		<position value="15px 0px"/>
		<size value="190px 25px" />
        <textVerticalAlignment value="middle" />
        <textAutoWidth value="true" />
		<textDisabledColor value="$preset_colorRed"/>
    </Profile>
	<Profile name="lpsLicensePlate" extends="fs25_textDefault" with="anchorTopRight">
		<size value="190px 25px" />
        <textVerticalAlignment value="middle" />
        <textAutoWidth value="true" />
        <position value="-10px 0" />
		<textAlignment value="right" />
		<textDisabledColor value="$preset_colorRed"/>
    </Profile>
</GUIProfiles>